colusa/__init__.py
colusa/_version.py
colusa/asciidoc_visitor.py
colusa/cli.py
colusa/colors.py
colusa/colusa.py
colusa/crawlers.py
colusa/etr.py
colusa/exceptions.py
colusa/fetch.py
colusa/logs.py
colusa/utils.py
colusa/visitor.py
colusa/plugins/__init__.py
colusa/plugins/etr_agilethought.py
colusa/plugins/etr_archive.py
colusa/plugins/etr_avikdas.py
colusa/plugins/etr_cadenceworkflow.py
colusa/plugins/etr_cs_rutgers_edu.py
colusa/plugins/etr_engineering_sportify.py
colusa/plugins/etr_eugeneyan.py
colusa/plugins/etr_fsblog.py
colusa/plugins/etr_hbr.py
colusa/plugins/etr_increment.py
colusa/plugins/etr_infoq.py
colusa/plugins/etr_knowledgegraph.py
colusa/plugins/etr_lethain.py
colusa/plugins/etr_linkedin.py
colusa/plugins/etr_medium.py
colusa/plugins/etr_metruyenchu.py
colusa/plugins/etr_morning.py
colusa/plugins/etr_paulg.py
colusa/plugins/etr_pragmatic_engineer.py
colusa/plugins/etr_preethikasireddy.py
colusa/plugins/etr_royalroad.py
colusa/plugins/etr_scrumcrazy.py
colusa/plugins/etr_sed.py
colusa/plugins/etr_slack_engineering.py
colusa/plugins/etr_staffeng.py
colusa/plugins/etr_tangthuvien.py
colusa/plugins/etr_techtarget.py
colusa/plugins/etr_trivago.py
colusa/plugins/etr_truyenfull.py
colusa/plugins/etr_unintendedconsequences.py
colusa/plugins/etr_untools.py
colusa/plugins/etr_wikipedia.py
colusa/plugins/etr_xp123.py
colusa/plugins/pp_regex.py
colusa-0.15.0.dist-info/licenses/LICENSE
colusa-0.15.0.dist-info/METADATA
colusa-0.15.0.dist-info/WHEEL
colusa-0.15.0.dist-info/entry_points.txt
colusa-0.15.0.dist-info/top_level.txt
colusa-0.15.0.dist-info/RECORD
