Metadata-Version: 2.4
Name: colusa
Version: 0.15.0
Summary: Render website to ebook to make it easier to read on devices
Author-email: Huu Hoa NGUYEN <huuhoa@gmail.com>
Maintainer-email: Huu Hoa NGUYEN <huuhoa@gmail.com>
License-Expression: MIT
Project-URL: Homepage, http://github.com/huuhoa/colusa
Project-URL: Repository, http://github.com/huuhoa/colusa
Project-URL: Bug Tracker, http://github.com/huuhoa/colusa/issues
Keywords: ebook,web,converter,asciidoc,epub
Classifier: Programming Language :: Python :: 3
Classifier: Programming Language :: Python :: 3.8
Classifier: Programming Language :: Python :: 3.9
Classifier: Programming Language :: Python :: 3.10
Classifier: Programming Language :: Python :: 3.11
Classifier: Programming Language :: Python :: 3.12
Classifier: Programming Language :: Python :: 3.13
Classifier: Operating System :: OS Independent
Classifier: Development Status :: 4 - Beta
Classifier: Intended Audience :: Developers
Classifier: Topic :: Text Processing :: Markup
Classifier: Topic :: Utilities
Requires-Python: >=3.8
License-File: LICENSE
Requires-Dist: beautifulsoup4>=4.9
Requires-Dist: certifi>=2025.8.3
Requires-Dist: chardet>=5.2.0
Requires-Dist: idna==3.10
Requires-Dist: requests>=2.32.4
Requires-Dist: soupsieve>=2.7
Requires-Dist: urllib3>=2.5.0
Requires-Dist: python-dateutil~=2.9.0
Requires-Dist: PyYAML>=6.0.1
Requires-Dist: torpy~=1.1.6
Requires-Dist: setuptools>=80.3.1
Requires-Dist: importlib-metadata; python_version < "3.10"
Provides-Extra: dev
Requires-Dist: bump2version>=1.0.1; extra == "dev"
Requires-Dist: gitchangelog>=3.0.4; extra == "dev"
Requires-Dist: readme-renderer>=44.0; extra == "dev"
Requires-Dist: twine>=6.1.0; extra == "dev"
Provides-Extra: test
Requires-Dist: pytest; extra == "test"
Requires-Dist: pytest-cov; extra == "test"
Provides-Extra: all
Requires-Dist: bump2version>=1.0.1; extra == "all"
Requires-Dist: gitchangelog>=3.0.4; extra == "all"
Requires-Dist: readme-renderer>=44.0; extra == "all"
Requires-Dist: twine>=6.1.0; extra == "all"
Requires-Dist: pytest; extra == "all"
Requires-Dist: pytest-cov; extra == "all"
Dynamic: license-file
